{
  "metadata": {
    "run_id": "run_20260219_084300",
    "timestamp": "2026-02-19T08:43:00.289016",
    "test_name": "API Encoding",
    "model": "llama-3.3-70b-versatile"
  },
  "success": true,
  "iterations": 2,
  "original_tokens": 1716,
  "final_tokens": 1572,
  "compression_ratio": 0.916083916083916,
  "final_similarity": 0.9257908463478088,
  "target_similarity": 0.8,
  "sections": {
    "count": 7,
    "breakdown": [
      {
        "title": "Database Migration Status",
        "importance": "critical",
        "tokens": 255,
        "content_preview": "Our PostgreSQL to Aurora migration is currently 73% complete. We've successfully migrated 847 tables..."
      },
      {
        "title": "Kubernetes Cluster Upgrade",
        "importance": "critical",
        "tokens": 201,
        "content_preview": "Our production Kubernetes clusters are running version 1.24, which reaches end-of-life on March 15th..."
      },
      {
        "title": "API Gateway Performance Issues",
        "importance": "high",
        "tokens": 195,
        "content_preview": "Our API Gateway (Kong) is experiencing memory leaks that cause instances to crash every 4-6 hours. T..."
      },
      {
        "title": "Monitoring & Observability Improvements",
        "importance": "medium",
        "tokens": 138,
        "content_preview": "Our current monitoring stack (Prometheus + Grafana) is struggling with the scale of metrics we're co..."
      },
      {
        "title": "Vulnerability Remediation",
        "importance": "critical",
        "tokens": 142,
        "content_preview": "Our latest security scan identified 47 high-severity vulnerabilities across our services: 23 in Node..."
      },
      {
        "title": "Infrastructure Costs",
        "importance": "medium",
        "tokens": 189,
        "content_preview": "Our AWS bill for January was $487,000, which is 18% over budget ($412,000). Main cost drivers: RDS A..."
      },
      {
        "title": "Action Items",
        "importance": "high",
        "tokens": 198,
        "content_preview": "Database Team (Lead: Sarah Chen): Implement table partitioning for user_sessions by Feb 15th, Increa..."
      }
    ]
  },
  "iteration_history": [
    {
      "iteration": 1,
      "similarity": 0.6630256175994873,
      "tokens": 422,
      "compression": 0.24592074592074592,
      "section_importances": [
        {
          "title": "Database Migration Status",
          "importance": "critical",
          "key_concepts": [
            "PostgreSQL",
            "Aurora migration",
            "Database performance"
          ]
        },
        {
          "title": "Kubernetes Cluster Upgrade",
          "importance": "critical",
          "key_concepts": [
            "Kubernetes upgrade",
            "PodSecurityPolicy",
            "Docker runtime"
          ]
        },
        {
          "title": "API Gateway Performance Issues",
          "importance": "high",
          "key_concepts": [
            "API Gateway",
            "Kong",
            "Rate limiting"
          ]
        },
        {
          "title": "Monitoring & Observability Improvements",
          "importance": "medium",
          "key_concepts": [
            "Prometheus",
            "Grafana",
            "Thanos"
          ]
        },
        {
          "title": "Vulnerability Remediation",
          "importance": "critical",
          "key_concepts": [
            "Security vulnerabilities",
            "CVE remediation",
            "Patch deployment"
          ]
        },
        {
          "title": "Infrastructure Costs",
          "importance": "medium",
          "key_concepts": [
            "AWS costs",
            "RDS Aurora",
            "EC2 instances"
          ]
        },
        {
          "title": "Action Items",
          "importance": "high",
          "key_concepts": [
            "Database team",
            "DevOps team",
            "Platform team"
          ]
        }
      ],
      "feedback": null
    },
    {
      "iteration": 2,
      "similarity": 0.9257908463478088,
      "tokens": 1572,
      "compression": 0.916083916083916,
      "section_importances": null,
      "feedback": "Here is the list of specific missing information:\n\n1. Missing facts, numbers, names:\n   - Specific details about the 23 deployments affected by the Kubernetes upgrade\n   - Names of team members responsible for each action item (except for team leads)\n   - Exact numbers of tables migrated and services affected by performance degradation\n   - Detailed breakdown of the $996,000 annual savings from infrastructure cost optimization\n\n2. Missing action items or deadlines:\n   - No specific deadline for implementing S3 lifecycle policies\n   - No deadline for optimizing data transfer with CloudFront\n   - No action item for investigating the 31% increase in data transfer costs\n\n3. Missing technical details:\n   - Technical specifications of the proposed Redis solution for rate limiting\n   - Details about the current indexing strategy and why it's insufficient\n   - Explanation of the \"hybrid approach\" for monitoring and observability improvements\n   - Technical requirements for upgrading PostgreSQL from 11 to 12\n\n4. Distorted or oversimplified information:\n   - The decoded message simplifies the complexity of the database migration status and the Kubernetes upgrade\n   - The decoded message does not provide the same level of detail as the original message regarding the API gateway performance issues and the proposed solutions\n   - The decoded message oversimplifies the infrastructure cost optimization opportunities and the estimated savings."
    }
  ],
  "texts": {
    "original": "Subject: Q1 2025 Engineering Roadmap & Critical Infrastructure Updates\n\nTeam,\n\nI'm writing to provide a comprehensive update on our Q1 2025 engineering priorities and address several critical infrastructure issues that require immediate attention. This is a detailed technical briefing, so please review carefully as there are action items for multiple teams.\n\nCRITICAL: Database Migration Status\n\nOur PostgreSQL to Aurora migration is currently 73% complete. We've successfully migrated 847 tables across 12 microservices, but we're experiencing significant performance degradation on three critical services: user-authentication-service, payment-processing-service, and analytics-aggregation-service.\n\nThe authentication service is seeing query latencies increase from an average of 45ms to 380ms, primarily on the user_sessions table which has grown to 2.3 billion rows. The current indexing strategy is insufficient for our read-heavy workload pattern. Database team has identified that we need to implement table partitioning by date range (monthly partitions) and add composite indexes on (user_id, created_at, session_status).\n\nPayment processing is even more concerning. We're seeing transaction timeouts affecting approximately 2.7% of all payment attempts, which translates to roughly $340,000 in failed transactions per day. Root cause analysis shows that our connection pool is exhausted during peak hours (2-4 PM EST and 7-9 PM EST). Current pool size is 150 connections per instance, but we're running 8 instances, and the Aurora cluster can handle up to 2000 concurrent connections. We need to increase pool size to 200 per instance and implement connection retry logic with exponential backoff.\n\nURGENT: Kubernetes Cluster Upgrade\n\nOur production Kubernetes clusters are running version 1.24, which reaches end-of-life on March 15th, 2025. We need to upgrade to 1.28 before the deadline. However, this upgrade has breaking changes that affect 23 of our deployments:\n\n1. PodSecurityPolicy has been removed - we need to migrate to Pod Security Standards\n2. Several API versions have been deprecated (batch/v1beta1, networking.k8s.io/v1beta1)\n3. Docker runtime support has been removed - we need to switch to containerd\n\nDevOps team has created a migration plan with three phases:\n- Phase 1 (Feb 10-17): Update all deployment manifests and test in staging\n- Phase 2 (Feb 18-24): Upgrade staging clusters and run full integration tests\n- Phase 3 (Feb 25-28): Rolling upgrade of production clusters with blue-green deployment strategy\n\nEstimated downtime: 15 minutes per cluster during off-peak hours (3-5 AM EST).\n\nHIGH PRIORITY: API Gateway Performance Issues\n\nOur API Gateway (Kong) is experiencing memory leaks that cause instances to crash every 4-6 hours. This is causing brief service disruptions (30-45 seconds) while the load balancer redirects traffic to healthy instances. \n\nInvestigation shows the issue is related to our custom rate-limiting plugin which is not properly releasing memory after processing requests. The plugin maintains an in-memory cache of rate limit counters that grows unbounded. We have two options:\n\nOption A: Rewrite the plugin to use Redis for rate limit storage (estimated 2 weeks development + 1 week testing)\nOption B: Upgrade to Kong 3.5 which has a built-in rate limiting plugin with better memory management (estimated 1 week testing + deployment)\n\nI'm recommending Option B as it's faster and reduces our custom code maintenance burden. However, Kong 3.5 requires PostgreSQL 12+ and we're currently on PostgreSQL 11.8, so we'd need to upgrade that first.\n\nMEDIUM PRIORITY: Monitoring & Observability Improvements\n\nOur current monitoring stack (Prometheus + Grafana) is struggling with the scale of metrics we're collecting. We're ingesting 45 million time series, and query performance has degraded significantly. Dashboard load times have increased from 2-3 seconds to 15-20 seconds.\n\nObservability team proposes migrating to a hybrid approach:\n- Keep Prometheus for real-time metrics (last 24 hours)\n- Use Thanos for long-term storage and historical queries\n- Implement metric aggregation to reduce cardinality by 60%\n\nEstimated cost: $12,000/month for Thanos infrastructure\nEstimated savings: $8,000/month from reduced Prometheus storage requirements\nNet cost increase: $4,000/month\n\nThis would also improve our incident response time by providing faster access to historical data for root cause analysis.\n\nSECURITY: Vulnerability Remediation\n\nOur latest security scan identified 47 high-severity vulnerabilities across our services:\n- 23 in Node.js dependencies (mostly transitive dependencies)\n- 12 in Python packages\n- 8 in container base images\n- 4 in Kubernetes configurations\n\nMost critical findings:\n1. CVE-2024-12345 in express.js (CVSS 9.8) - allows remote code execution\n2. CVE-2024-67890 in lodash (CVSS 8.1) - prototype pollution vulnerability\n3. Several containers running as root user (violates security best practices)\n\nSecurity team requires all high-severity vulnerabilities to be patched within 14 days (deadline: February 28th). This will require coordinated updates across 34 services.\n\nINFRASTRUCTURE COSTS\n\nOur AWS bill for January was $487,000, which is 18% over budget ($412,000). Main cost drivers:\n- RDS Aurora: $142,000 (up 23% from December due to increased read replicas)\n- EC2 instances: $178,000 (up 15% from December due to auto-scaling during holiday traffic)\n- Data transfer: $89,000 (up 31% from December - need to investigate)\n- S3 storage: $45,000 (steady)\n\nFinOps team has identified several optimization opportunities:\n1. Right-size EC2 instances - estimated savings: $25,000/month\n2. Use Reserved Instances for baseline capacity - estimated savings: $35,000/month\n3. Implement S3 lifecycle policies - estimated savings: $8,000/month\n4. Optimize data transfer with CloudFront - estimated savings: $15,000/month\n\nTotal potential savings: $83,000/month ($996,000 annually)\n\nACTION ITEMS\n\n1. Database Team (Lead: Sarah Chen)\n   - Implement table partitioning for user_sessions by Feb 15th\n   - Increase connection pool sizes by Feb 12th\n   - Monitor and report on performance improvements\n\n2. DevOps Team (Lead: Marcus Rodriguez)\n   - Complete Kubernetes upgrade plan by Feb 10th\n   - Execute staging upgrade by Feb 24th\n   - Coordinate production upgrade Feb 25-28th\n\n3. Platform Team (Lead: Jennifer Kim)\n   - Evaluate Kong 3.5 upgrade path by Feb 8th\n   - Plan PostgreSQL 11 to 12 upgrade by Feb 10th\n   - Execute Kong upgrade by Feb 20th\n\n4. Security Team (Lead: David Park)\n   - Prioritize CVE remediation by severity\n   - Coordinate with service owners for patching\n   - Verify all patches deployed by Feb 28th\n\n5. FinOps Team (Lead: Amanda Foster)\n   - Present detailed cost optimization plan by Feb 12th\n   - Implement quick wins (right-sizing) by Feb 15th\n   - Execute Reserved Instance purchases by Feb 20th\n\nTIMELINE SUMMARY\n\nWeek of Feb 5-9:\n- Database partitioning implementation\n- Kong upgrade evaluation\n- Cost optimization planning\n\nWeek of Feb 12-16:\n- Connection pool increases\n- Kubernetes manifest updates\n- Security patching begins\n\nWeek of Feb 19-23:\n- Staging Kubernetes upgrade\n- Kong upgrade execution\n- Reserved Instance purchases\n\nWeek of Feb 26-Mar 1:\n- Production Kubernetes upgrade\n- Final security patch verification\n- Cost optimization review\n\nPlease review your team's action items and confirm feasibility by end of day Friday. We'll have a technical deep-dive meeting on Monday, February 5th at 10 AM EST to discuss any concerns or blockers.\n\nIf you have questions or need clarification on any of these items, please reach out directly or post in the #engineering-leadership Slack channel.\n\nThanks,\nAlex Thompson\nVP of Engineering\n",
    "final_decoded": "**Q1 2025 Engineering Roadmap & Critical Infrastructure Updates Report**\n\nThe current status of our Q1 2025 engineering roadmap and critical infrastructure updates is critical, with ongoing progress towards meeting the deadline of March 15th, 2025. This report highlights the key areas of focus, including database migration, Kubernetes cluster upgrade, API gateway performance issues, monitoring and observability improvements, vulnerability remediation, infrastructure costs, and action items.\n\n### Database Migration Status\n\nOur PostgreSQL to Aurora migration is currently 73% complete, with 847 tables successfully migrated across 12 microservices. However, we are experiencing significant performance degradation on three critical services: user-authentication-service, payment-processing-service, and analytics-aggregation-service. The authentication service is seeing query latencies increase from an average of 45ms to 380ms, primarily due to the insufficient indexing strategy for our read-heavy workload pattern. To address this, we need to implement table partitioning by date range (monthly partitions) and add composite indexes on (user_id, created_at, session_status).\n\nThe payment processing service is also experiencing issues, with transaction timeouts affecting approximately 2.7% of all payment attempts, resulting in roughly $340,000 in failed transactions per day. The root cause analysis shows that our connection pool is exhausted during peak hours, and we need to increase the pool size to 200 per instance and implement connection retry logic with exponential backoff.\n\n### Kubernetes Cluster Upgrade\n\nOur production Kubernetes clusters are running version 1.24, which reaches end-of-life on March 15th, 2025. We need to upgrade to version 1.28 before the deadline. However, this upgrade has breaking changes that affect 23 of our deployments, including the removal of PodSecurityPolicy, deprecation of several API versions, and removal of Docker runtime support. The DevOps team has created a migration plan with three phases: Phase 1 (Feb 10-17): Update all deployment manifests and test in staging, Phase 2 (Feb 18-24): Upgrade staging clusters and run full integration tests, Phase 3 (Feb 25-28): Rolling upgrade of production clusters with blue-green deployment strategy. The estimated downtime is 15 minutes per cluster during off-peak hours.\n\n### API Gateway Performance Issues\n\nOur API Gateway (Kong) is experiencing memory leaks that cause instances to crash every 4-6 hours, resulting in brief service disruptions. The investigation shows that the issue is related to our custom rate-limiting plugin, which is not properly releasing memory after processing requests. We have two options: Rewrite the plugin to use Redis for rate limit storage or upgrade to Kong 3.5, which has a built-in rate limiting plugin with better memory management. We recommend upgrading to Kong 3.5, but this requires PostgreSQL 12+, and we are currently on PostgreSQL 11.8, so we need to upgrade that first.\n\n### Monitoring & Observability Improvements\n\nOur current monitoring stack (Prometheus + Grafana) is struggling with the scale of metrics we're collecting, resulting in degraded query performance and increased dashboard load times. The Observability team proposes migrating to a hybrid approach: Keep Prometheus for real-time metrics (last 24 hours), use Thanos for long-term storage and historical queries, and implement metric aggregation to reduce cardinality by 60%. The estimated cost is $12,000/month for Thanos infrastructure, with estimated savings of $8,000/month from reduced Prometheus storage requirements, resulting in a net cost increase of $4,000/month.\n\n### Vulnerability Remediation\n\nOur latest security scan identified 47 high-severity vulnerabilities across our services, including 23 in Node.js dependencies, 12 in Python packages, 8 in container base images, and 4 in Kubernetes configurations. The most critical findings include CVE-2024-12345 in express.js, which allows remote code execution, and CVE-2024-67890 in lodash, which is a prototype pollution vulnerability. The Security team requires all high-severity vulnerabilities to be patched within 14 days (deadline: February 28th), which will require coordinated updates across 34 services.\n\n### Infrastructure Costs\n\nOur AWS bill for January was $487,000, which is 18% over budget ($412,000). The main cost drivers are RDS Aurora, EC2 instances, data transfer, and S3 storage. The FinOps team has identified several optimization opportunities, including right-sizing EC2 instances, using Reserved Instances for baseline capacity, implementing S3 lifecycle policies, and optimizing data transfer with CloudFront. The total potential savings are $83,000/month ($996,000 annually).\n\n### Action Items\n\nThe following action items have been assigned:\n\n* Database Team (Lead: Sarah Chen): Implement table partitioning for user_sessions by Feb 15th, increase connection pool sizes by Feb 12th, and monitor and report on performance improvements.\n* DevOps Team (Lead: Marcus Rodriguez): Complete Kubernetes upgrade plan by Feb 10th, execute staging upgrade by Feb 24th, and coordinate production upgrade Feb 25-28th.\n* Platform Team (Lead: Jennifer Kim): Evaluate Kong 3.5 upgrade path by Feb 8th, plan PostgreSQL 11 to 12 upgrade by Feb 10th, and execute Kong upgrade by Feb 20th.\n* Security Team (Lead: David Park): Prioritize CVE remediation by severity, coordinate with service owners for patching, and verify all patches deployed by Feb 28th.\n* FinOps Team (Lead: Amanda Foster): Present detailed cost optimization plan by Feb 12th, implement quick wins (right-sizing) by Feb 15th, and execute Reserved Instance purchases by Feb 20th.\n\nThe deadlines for these action items are February 28th, 2025, and March 15th, 2025, with a budget of $412,000. The current status of the project is ongoing, and we are working to complete all tasks within the given timeframe.",
    "final_signal_json": "{\n  \"version\": \"2.0\",\n  \"intent\": \"REPORT\",\n  \"target\": \"Q1 2025 Engineering Roadmap & Critical Infrastructure Updates\",\n  \"priority\": \"high\",\n  \"summary\": {\n    \"status\": \"critical\",\n    \"progress\": \"ongoing\",\n    \"deadline\": \"March 15th, 2025\"\n  },\n  \"sections\": [\n    {\n      \"title\": \"Database Migration Status\",\n      \"content\": \"Our PostgreSQL to Aurora migration is currently 73% complete. We've successfully migrated 847 tables across 12 microservices, but we're experiencing significant performance degradation on three critical services: user-authentication-service, payment-processing-service, and analytics-aggregation-service. The authentication service is seeing query latencies increase from an average of 45ms to 380ms, primarily on the user_sessions table which has grown to 2.3 billion rows. The current indexing strategy is insufficient for our read-heavy workload pattern. Database team has identified that we need to implement table partitioning by date range (monthly partitions) and add composite indexes on (user_id, created_at, session_status). Payment processing is even more concerning. We're seeing transaction timeouts affecting approximately 2.7% of all payment attempts, which translates to roughly $340,000 in failed transactions per day. Root cause analysis shows that our connection pool is exhausted during peak hours (2-4 PM EST and 7-9 PM EST). Current pool size is 150 connections per instance, but we're running 8 instances, and the Aurora cluster can handle up to 2000 concurrent connections. We need to increase pool size to 200 per instance and implement connection retry logic with exponential backoff.\",\n      \"importance\": \"critical\"\n    },\n    {\n      \"title\": \"Kubernetes Cluster Upgrade\",\n      \"content\": \"Our production Kubernetes clusters are running version 1.24, which reaches end-of-life on March 15th, 2025. We need to upgrade to 1.28 before the deadline. However, this upgrade has breaking changes that affect 23 of our deployments: PodSecurityPolicy has been removed - we need to migrate to Pod Security Standards, several API versions have been deprecated (batch/v1beta1, networking.k8s.io/v1beta1), and Docker runtime support has been removed - we need to switch to containerd. DevOps team has created a migration plan with three phases: Phase 1 (Feb 10-17): Update all deployment manifests and test in staging, Phase 2 (Feb 18-24): Upgrade staging clusters and run full integration tests, Phase 3 (Feb 25-28): Rolling upgrade of production clusters with blue-green deployment strategy. Estimated downtime: 15 minutes per cluster during off-peak hours (3-5 AM EST).\",\n      \"importance\": \"critical\"\n    },\n    {\n      \"title\": \"API Gateway Performance Issues\",\n      \"content\": \"Our API Gateway (Kong) is experiencing memory leaks that cause instances to crash every 4-6 hours. This is causing brief service disruptions (30-45 seconds) while the load balancer redirects traffic to healthy instances. Investigation shows the issue is related to our custom rate-limiting plugin which is not properly releasing memory after processing requests. The plugin maintains an in-memory cache of rate limit counters that grows unbounded. We have two options: Option A: Rewrite the plugin to use Redis for rate limit storage (estimated 2 weeks development + 1 week testing), Option B: Upgrade to Kong 3.5 which has a built-in rate limiting plugin with better memory management (estimated 1 week testing + deployment). I'm recommending Option B as it's faster and reduces our custom code maintenance burden. However, Kong 3.5 requires PostgreSQL 12+ and we're currently on PostgreSQL 11.8, so we'd need to upgrade that first.\",\n      \"importance\": \"high\"\n    },\n    {\n      \"title\": \"Monitoring & Observability Improvements\",\n      \"content\": \"Our current monitoring stack (Prometheus + Grafana) is struggling with the scale of metrics we're collecting. We're ingesting 45 million time series, and query performance has degraded significantly. Dashboard load times have increased from 2-3 seconds to 15-20 seconds. Observability team proposes migrating to a hybrid approach: Keep Prometheus for real-time metrics (last 24 hours), Use Thanos for long-term storage and historical queries, Implement metric aggregation to reduce cardinality by 60%. Estimated cost: $12,000/month for Thanos infrastructure, Estimated savings: $8,000/month from reduced Prometheus storage requirements, Net cost increase: $4,000/month.\",\n      \"importance\": \"medium\"\n    },\n    {\n      \"title\": \"Vulnerability Remediation\",\n      \"content\": \"Our latest security scan identified 47 high-severity vulnerabilities across our services: 23 in Node.js dependencies (mostly transitive dependencies), 12 in Python packages, 8 in container base images, 4 in Kubernetes configurations. Most critical findings: CVE-2024-12345 in express.js (CVSS 9.8) - allows remote code execution, CVE-2024-67890 in lodash (CVSS 8.1) - prototype pollution vulnerability, Several containers running as root user (violates security best practices). Security team requires all high-severity vulnerabilities to be patched within 14 days (deadline: February 28th). This will require coordinated updates across 34 services.\",\n      \"importance\": \"critical\"\n    },\n    {\n      \"title\": \"Infrastructure Costs\",\n      \"content\": \"Our AWS bill for January was $487,000, which is 18% over budget ($412,000). Main cost drivers: RDS Aurora: $142,000 (up 23% from December due to increased read replicas), EC2 instances: $178,000 (up 15% from December due to auto-scaling during holiday traffic), Data transfer: $89,000 (up 31% from December - need to investigate), S3 storage: $45,000 (steady). FinOps team has identified several optimization opportunities: Right-size EC2 instances - estimated savings: $25,000/month, Use Reserved Instances for baseline capacity - estimated savings: $35,000/month, Implement S3 lifecycle policies - estimated savings: $8,000/month, Optimize data transfer with CloudFront - estimated savings: $15,000/month. Total potential savings: $83,000/month ($996,000 annually).\",\n      \"importance\": \"medium\"\n    },\n    {\n      \"title\": \"Action Items\",\n      \"content\": \"Database Team (Lead: Sarah Chen): Implement table partitioning for user_sessions by Feb 15th, Increase connection pool sizes by Feb 12th, Monitor and report on performance improvements. DevOps Team (Lead: Marcus Rodriguez): Complete Kubernetes upgrade plan by Feb 10th, Execute staging upgrade by Feb 24th, Coordinate production upgrade Feb 25-28th. Platform Team (Lead: Jennifer Kim): Evaluate Kong 3.5 upgrade path by Feb 8th, Plan PostgreSQL 11 to 12 upgrade by Feb 10th, Execute Kong upgrade by Feb 20th. Security Team (Lead: David Park): Prioritize CVE remediation by severity, Coordinate with service owners for patching, Verify all patches deployed by Feb 28th. FinOps Team (Lead: Amanda Foster): Present detailed cost optimization plan by Feb 12th, Implement quick wins (right-sizing) by Feb 15th, Execute Reserved Instance purchases by Feb 20th.\",\n      \"importance\": \"high\"\n    }\n  ],\n  \"constraints\": [\n    \"deadlines: ['February 28th, 2025', 'March 15th, 2025']\",\n    \"budget: $412,000\"\n  ],\n  \"state\": {\n    \"status\": \"ongoing\"\n  },\n  \"encoding_strategy\": \"chunked\",\n  \"total_sections\": 7,\n  \"trace_id\": \"065eaa5f-4763-4175-9b8a-e4bf5b373155\",\n  \"timestamp\": \"2026-02-19T08:42:48.622295\",\n  \"parent_id\": null\n}"
  }
}