{
  "metadata": {
    "run_id": "run_20260219_092655",
    "timestamp": "2026-02-19T09:26:55.490386",
    "test_name": "API Encoding",
    "model": "llama-3.3-70b-versatile"
  },
  "success": true,
  "iterations": 2,
  "original_tokens": 2209,
  "decoded_tokens": 1164,
  "signal_tokens": 1024,
  "final_tokens": 1164,
  "compression_ratio": 0.526935264825713,
  "compression_percentage": 47.30647351742871,
  "final_similarity": 0.9152294397354126,
  "target_similarity": 0.9,
  "sections": {
    "count": 7,
    "breakdown": [
      {
        "title": "Executive Summary",
        "importance": "critical",
        "tokens": 130,
        "content_preview": "On January 15, 2025, at 14:23 UTC, our primary production environment experienced a complete service..."
      },
      {
        "title": "Timeline of Events",
        "importance": "high",
        "tokens": 171,
        "content_preview": "14:23 UTC - Initial alerts triggered for elevated API response times in the us-east-1 region. Averag..."
      },
      {
        "title": "Root Cause Analysis",
        "importance": "critical",
        "tokens": 134,
        "content_preview": "The incident was caused by a combination of factors: CODE DEFECT - The analytics batch job contained..."
      },
      {
        "title": "Impact Assessment",
        "importance": "high",
        "tokens": 127,
        "content_preview": "CUSTOMER IMPACT: 2.3 million active users affected, 4 hours 37 minutes of complete service unavailab..."
      },
      {
        "title": "Corrective Actions",
        "importance": "high",
        "tokens": 116,
        "content_preview": "IMMEDIATE: Rolled back analytics batch job to version 2.3.8, Implemented emergency monitoring for da..."
      },
      {
        "title": "Lessons Learned",
        "importance": "medium",
        "tokens": 43,
        "content_preview": "MONITORING IS CRITICAL, TESTING MUST REFLECT PRODUCTION, DEPLOYMENT TIMING MATTERS, CODE REVIEW QUAL..."
      },
      {
        "title": "Recommendations",
        "importance": "medium",
        "tokens": 25,
        "content_preview": "Invest in observability infrastructure, Hire dedicated SRE team, Implement mandatory chaos engineeri..."
      }
    ]
  },
  "iteration_history": [
    {
      "iteration": 1,
      "similarity": 0.7943428754806519,
      "tokens": 727,
      "compression": 0.32910819375282935,
      "section_importances": [
        {
          "title": "Executive Summary",
          "importance": "critical",
          "key_concepts": [
            "Production Outage",
            "Database Connection Pool Exhaustion",
            "Revenue Impact"
          ]
        },
        {
          "title": "Timeline of Events",
          "importance": "high",
          "key_concepts": [
            "Incident Timeline",
            "API Response Times",
            "Database Connection Pool Utilization"
          ]
        },
        {
          "title": "Root Cause Analysis",
          "importance": "critical",
          "key_concepts": [
            "Code Defect",
            "Insufficient Testing",
            "Monitoring Gaps"
          ]
        },
        {
          "title": "Impact Assessment",
          "importance": "high",
          "key_concepts": [
            "Customer Impact",
            "Financial Impact",
            "Operational Impact"
          ]
        },
        {
          "title": "Corrective Actions",
          "importance": "high",
          "key_concepts": [
            "Immediate Actions",
            "Short-term Actions",
            "Medium-term Actions"
          ]
        },
        {
          "title": "Lessons Learned",
          "importance": "medium",
          "key_concepts": [
            "Monitoring",
            "Testing",
            "Deployment Timing"
          ]
        },
        {
          "title": "Recommendations",
          "importance": "medium",
          "key_concepts": [
            "Observability Infrastructure",
            "SRE Team",
            "Chaos Engineering"
          ]
        }
      ],
      "feedback": "Here are the specific missing information with examples:\n\n1. MISSING: $340,000 in SLA credits owed to enterprise customers\n2. MISSING: Names of specific team members such as Sarah Martinez, James Kim, Aisha Patel, Rebecca Torres, and David Liu\n3. MISSING: Specific date for the emergency war room establishment (only time is mentioned: 14:38 UTC)\n4. MISSING: Action items such as \"emergency war room established on Zoom\" and \"incident commander role assumed by VP Engineering Marcus Chen\"\n5. MISSING: Technical details such as \"average response time increased from baseline 120ms to 3,400ms\" and \"load balancer health checks started failing for 12 of 45 application servers\"\n6. MISSING: Detailed timeline of events, including the initial hypothesis of a DDoS attack and the subsequent ruling out of this hypothesis\n7. MISSING: Specific number of active users affected across North America and Europe (only mentioned as \"approximately 2.3 million\")\n8. MISSING: Detailed financial breakdown, including the estimated revenue impact of $1.2 million (only mentioned briefly)\n9. MISSING: Specific details about the database connection pool exhaustion, such as the number of connections active (490 of 500)\n10. MISSING: Specific details about the misconfigured CloudWatch alarm threshold (set at 99% instead of 90%)\n\nThese specific facts and details are present in the original message but are missing or oversimplified in the decoded message."
    },
    {
      "iteration": 2,
      "similarity": 0.9152294397354126,
      "tokens": 1024,
      "compression": 0.463558171118153,
      "section_importances": null,
      "feedback": null
    }
  ],
  "texts": {
    "original": "INCIDENT REPORT: Critical Production Outage - January 15, 2025\n\nEXECUTIVE SUMMARY\n\nOn January 15, 2025, at 14:23 UTC, our primary production environment experienced a complete service outage lasting 4 hours and 37 minutes, affecting approximately 2.3 million active users across North America and Europe. The root cause was identified as a cascading failure triggered by a database connection pool exhaustion, compounded by inadequate circuit breaker configuration and insufficient monitoring alerts. Total estimated revenue impact is $1.2 million, with an additional $340,000 in SLA credits owed to enterprise customers.\n\nTIMELINE OF EVENTS\n\n14:23 UTC - Initial alerts triggered for elevated API response times in the us-east-1 region. Average response time increased from baseline 120ms to 3,400ms. On-call engineer Sarah Martinez received PagerDuty notification.\n\n14:26 UTC - Database connection pool utilization reached 98% (490 of 500 connections active). Application servers began queuing requests. No automatic scaling triggered due to misconfigured CloudWatch alarm threshold (set at 99% instead of 90%).\n\n14:31 UTC - First customer complaints received via support channels. Customer success team escalated to engineering. Load balancer health checks started failing for 12 of 45 application servers.\n\n14:35 UTC - Complete service outage declared. All API endpoints returning 503 errors. Mobile applications unable to sync data. Web dashboard inaccessible. Incident commander role assumed by VP Engineering Marcus Chen.\n\n14:38 UTC - Emergency war room established on Zoom. Participants: Marcus Chen (Incident Commander), Sarah Martinez (Database Lead), James Kim (Infrastructure), Aisha Patel (Application Lead), Rebecca Torres (Customer Success), David Liu (Communications).\n\n14:42 UTC - Initial hypothesis: DDoS attack. Security team analyzed traffic patterns. Ruled out after confirming legitimate user traffic distribution matched historical patterns.\n\n14:51 UTC - Database team identified connection pool exhaustion. Attempted to increase pool size from 500 to 1000 connections. Change required application restart, which was deemed too risky during active incident.\n\n15:03 UTC - Root cause identified: A batch job processing user analytics data, deployed at 13:45 UTC, was opening database connections without proper connection pooling. Each job instance was creating 50+ connections and not releasing them. The job was processing 2.4 million user records.\n\n15:08 UTC - Decision made to kill the problematic batch job processes. DevOps team identified 23 running instances across the cluster.\n\n15:15 UTC - All batch job instances terminated. Database connection pool utilization dropped to 67%. API response times began improving but remained elevated at 1,200ms.\n\n15:23 UTC - Application servers gradually recovering. Health checks passing for 38 of 45 servers. Remaining 7 servers required manual restart due to corrupted connection pool state.\n\n15:45 UTC - Service partially restored. 85% of traffic being served successfully. Remaining issues isolated to specific geographic regions due to DNS propagation delays.\n\n16:18 UTC - Full service restoration confirmed. All health checks passing. API response times returned to baseline 120ms. Database connection pool stable at 340 connections (68% utilization).\n\n16:45 UTC - Incident officially closed. Post-incident monitoring period initiated.\n\n19:00 UTC - All-hands post-mortem meeting scheduled for January 16, 09:00 UTC.\n\nROOT CAUSE ANALYSIS\n\nThe incident was caused by a combination of factors:\n\n1. CODE DEFECT: The analytics batch job (version 2.4.1, deployed January 15 at 13:45 UTC) contained a critical bug where database connections were created in a loop without using the connection pool manager. The code review process failed to catch this issue because the reviewer was unfamiliar with the connection pooling library.\n\n2. INSUFFICIENT TESTING: The batch job was tested in staging environment with only 10,000 sample records, which did not expose the connection leak. Production processes 2.4 million records, 240x larger than test dataset.\n\n3. MONITORING GAPS: No alerts configured for database connection pool utilization. Existing alerts only monitored CPU and memory, not connection pool metrics. The first alert triggered was for API response time, which was a downstream symptom rather than the root cause.\n\n4. CIRCUIT BREAKER MISCONFIGURATION: Application-level circuit breakers were configured with a 60-second timeout and 50-failure threshold. These settings were too permissive, allowing the cascading failure to propagate before circuit breakers opened.\n\n5. DEPLOYMENT PROCESS: The batch job was deployed during peak business hours (2:45 PM EST / 14:45 UTC) without following the standard deployment window policy (deployments should occur during off-peak hours: 22:00-04:00 UTC).\n\nIMPACT ASSESSMENT\n\nCUSTOMER IMPACT:\n- 2.3 million active users affected (87% of total user base)\n- 4 hours 37 minutes of complete service unavailability\n- 847 support tickets created during incident\n- 234 enterprise customers affected, requiring SLA credit compensation\n- Net Promoter Score dropped from 68 to 41 in post-incident survey\n- 12 enterprise customers threatened contract cancellation\n- Social media sentiment analysis showed 3,400 negative mentions\n\nFINANCIAL IMPACT:\n- Direct revenue loss: $1,200,000 (based on average revenue per hour)\n- SLA credits owed: $340,000 (enterprise customers with 99.9% uptime guarantee)\n- Support overtime costs: $23,000 (additional staff called in)\n- Engineering overtime: $18,000\n- Total financial impact: $1,581,000\n\nOPERATIONAL IMPACT:\n- 47 engineers pulled from planned work to assist with incident\n- Q1 roadmap delayed by 1 week to implement preventive measures\n- 3 customer implementations postponed\n- Security audit scheduled for January 20 had to be rescheduled\n\nCORRECTIVE ACTIONS\n\nIMMEDIATE (Completed within 24 hours):\n1. Rolled back analytics batch job to version 2.3.8 (stable version)\n2. Implemented emergency monitoring for database connection pool utilization with alerts at 70%, 80%, and 90% thresholds\n3. Reduced circuit breaker timeout from 60s to 10s and failure threshold from 50 to 10\n4. Increased database connection pool size from 500 to 800 with auto-scaling enabled\n5. Created runbook for connection pool exhaustion scenarios\n\nSHORT-TERM (Complete within 1 week):\n1. Comprehensive code review of all batch jobs for connection management issues (Owner: Aisha Patel, Due: January 22)\n2. Implement connection pool monitoring dashboard with real-time visualization (Owner: James Kim, Due: January 20)\n3. Update deployment policy to enforce off-peak deployment windows with automated checks (Owner: DevOps team, Due: January 23)\n4. Conduct training session on connection pooling best practices for all backend engineers (Owner: Sarah Martinez, Due: January 24)\n5. Implement automated testing requirements: staging tests must use production-scale data samples (minimum 10% of production volume) (Owner: QA team, Due: January 25)\n\nMEDIUM-TERM (Complete within 1 month):\n1. Implement distributed tracing to identify connection leaks in real-time (Owner: Platform team, Due: February 10)\n2. Deploy chaos engineering tests to validate circuit breaker behavior under load (Owner: SRE team, Due: February 15)\n3. Upgrade database infrastructure to support 2000 concurrent connections with automatic failover (Owner: Database team, Due: February 20)\n4. Implement automated rollback triggers based on error rate thresholds (Owner: DevOps, Due: February 12)\n5. Create customer communication templates for various incident scenarios (Owner: Customer Success, Due: February 5)\n\nLONG-TERM (Complete within 3 months):\n1. Migrate to microservices architecture to isolate batch job failures from API services (Owner: Architecture team, Due: April 15)\n2. Implement comprehensive observability platform with distributed tracing, metrics, and logs (Owner: Platform team, Due: March 30)\n3. Establish formal incident response training program with quarterly drills (Owner: SRE team, Due: March 15)\n4. Deploy multi-region active-active architecture to eliminate single points of failure (Owner: Infrastructure team, Due: April 30)\n\nLESSONS LEARNED\n\n1. MONITORING IS CRITICAL: We learned that monitoring downstream symptoms (API response time) is insufficient. We must monitor all critical resources at the source, including database connections, thread pools, and memory allocation.\n\n2. TESTING MUST REFLECT PRODUCTION: Staging environment testing with 10,000 records failed to expose issues that manifested with 2.4 million records. Test data volume must be representative of production scale.\n\n3. DEPLOYMENT TIMING MATTERS: Deploying during peak hours (14:45 UTC) maximized customer impact. Strict enforcement of deployment windows is essential.\n\n4. CODE REVIEW QUALITY: The connection leak bug should have been caught in code review. We need better training and potentially automated static analysis tools to catch resource management issues.\n\n5. CIRCUIT BREAKERS NEED TUNING: Our circuit breaker settings were too permissive. We need to regularly test and tune these configurations based on actual system behavior.\n\n6. INCIDENT RESPONSE WORKED WELL: Despite the severity, our incident response process was effective. War room established quickly, clear roles assigned, systematic troubleshooting approach. We should document and reinforce these practices.\n\nRECOMMENDATIONS\n\n1. Invest in observability infrastructure: Budget $250,000 for comprehensive monitoring and tracing platform\n2. Hire dedicated SRE team: Add 3 Site Reliability Engineers to focus on system resilience\n3. Implement mandatory chaos engineering: Monthly chaos tests to validate system resilience\n4. Upgrade staging environment: Match production scale to enable realistic testing\n5. Establish incident response training: Quarterly drills for all engineering staff\n\nCONCLUSION\n\nThis incident exposed critical gaps in our infrastructure monitoring, testing practices, and deployment processes. While the immediate impact was severe, the corrective actions we're implementing will significantly improve our system resilience. The incident response team performed admirably under pressure, and we should recognize their efforts while learning from the systemic issues that allowed this incident to occur.\n\nAll corrective actions are being tracked in JIRA project INCIDENT-2025-001. Weekly status updates will be provided to executive leadership until all actions are complete.\n\nReport prepared by: Marcus Chen, VP Engineering\nDate: January 16, 2025\nDistribution: Executive Team, Engineering Leadership, Board of Directors\nClassification: Internal - Confidential\n",
    "final_decoded": "**Critical Production Outage - January 15, 2025**\n\n### Executive Summary\n\nOn January 15, 2025, at 14:23 UTC, our primary production environment experienced a complete service outage lasting 4 hours and 37 minutes, affecting approximately 2.3 million active users across North America and Europe. The root cause was identified as a cascading failure triggered by a database connection pool exhaustion, compounded by inadequate circuit breaker configuration and insufficient monitoring alerts. Total estimated revenue impact is $1.2 million, with an additional $340,000 in SLA credits owed to enterprise customers. Key team members involved in the incident response and resolution included Sarah Martinez, James Kim, Aisha Patel, Rebecca Torres, David Liu, and Marcus Chen.\n\n### Timeline of Events\n\nThe incident timeline is as follows:\n- 14:23 UTC: Initial alerts were triggered for elevated API response times in the us-east-1 region, with the average response time increasing from a baseline of 120ms to 3,400ms. On-call engineer Sarah Martinez received a PagerDuty notification.\n- 14:26 UTC: Database connection pool utilization reached 98% (490 of 500 connections active).\n- 14:31 UTC: The first customer complaints were received via support channels.\n- 14:35 UTC: A complete service outage was declared.\n- 14:38 UTC: An emergency war room was established on Zoom with participants including Marcus Chen, Sarah Martinez, James Kim, Aisha Patel, Rebecca Torres, and David Liu. The initial hypothesis was a DDoS attack, which was later ruled out. The root cause was identified as a batch job processing user analytics data, deployed at 13:45 UTC, which was opening database connections without proper connection pooling.\n\n### Root Cause Analysis\n\nThe incident was caused by a combination of factors:\n- **CODE DEFECT**: The analytics batch job contained a critical bug where database connections were created in a loop without using the connection pool manager.\n- **INSUFFICIENT TESTING**: The batch job was tested in a staging environment with only 10,000 sample records, which did not expose the connection leak.\n- **MONITORING GAPS**: No alerts were configured for database connection pool utilization.\n- **CIRCUIT BREAKER MISCONFIGURATION**: Application-level circuit breakers were configured with a 60-second timeout and a 50-failure threshold.\n- **DEPLOYMENT PROCESS**: The batch job was deployed during peak business hours without following the standard deployment window policy.\n\n### Impact Assessment\n\nThe impact of the incident was significant:\n- **CUSTOMER IMPACT**: 2.3 million active users were affected, with 4 hours and 37 minutes of complete service unavailability. A total of 847 support tickets were created, and 234 enterprise customers were affected, requiring SLA credit compensation.\n- **FINANCIAL IMPACT**: The direct revenue loss was $1,200,000, with $340,000 in SLA credits owed. Additional costs included $23,000 for support overtime and $18,000 for engineering overtime, resulting in a total financial impact of $1,581,000.\n- **OPERATIONAL IMPACT**: 47 engineers were pulled from planned work, the Q1 roadmap was delayed by 1 week, and 3 customer implementations were postponed.\n\n### Corrective Actions\n\nTo prevent similar incidents in the future, the following corrective actions were taken:\n- **IMMEDIATE**: The analytics batch job was rolled back to version 2.3.8, emergency monitoring for database connection pool utilization was implemented, the circuit breaker timeout was reduced, and the database connection pool size was increased.\n- **SHORT-TERM**: A comprehensive code review of all batch jobs will be conducted, a connection pool monitoring dashboard will be implemented, the deployment policy will be updated, and a training session on connection pooling best practices will be conducted.\n- **MEDIUM-TERM**: Distributed tracing will be implemented, chaos engineering tests will be deployed, the database infrastructure will be upgraded, and automated rollback triggers will be implemented.\n- **LONG-TERM**: The system will be migrated to a microservices architecture, a comprehensive observability platform will be implemented, and a formal incident response training program will be established.\n\n### Lessons Learned\n\nKey lessons learned from the incident include:\n- **MONITORING IS CRITICAL**: Adequate monitoring is essential to detect issues before they cause significant impact.\n- **TESTING MUST REFLECT PRODUCTION**: Testing should reflect real-world scenarios to ensure that issues are caught before deployment.\n- **DEPLOYMENT TIMING MATTERS**: Deployments should be scheduled during maintenance windows to minimize the impact of potential issues.\n- **CODE REVIEW QUALITY**: High-quality code reviews are crucial to catch defects before they reach production.\n- **CIRCUIT BREAKERS NEED TUNING**: Circuit breakers should be properly configured to prevent cascading failures.\n- **INCIDENT RESPONSE WORKED WELL**: The incident response process was effective in mitigating the impact of the incident.\n\n### Recommendations\n\nBased on the incident, the following recommendations are made:\n- Invest in observability infrastructure to improve monitoring and detection capabilities.\n- Hire a dedicated SRE team to focus on system reliability and performance.\n- Implement mandatory chaos engineering to test the system's resilience.\n- Upgrade the staging environment to better reflect production conditions.\n- Establish incident response training to ensure that teams are prepared to handle future incidents.\n\nThe incident status is currently closed, with post-incident monitoring in progress. All corrective actions are to be completed within specified deadlines, and comprehensive monitoring and alerting for database connection pool utilization will be enforced. The standard deployment window policy will also be strictly followed to prevent similar incidents in the future.",
    "final_signal_json": "{\n  \"version\": \"2.0\",\n  \"intent\": \"REPORT\",\n  \"target\": \"Critical Production Outage - January 15, 2025\",\n  \"priority\": \"high\",\n  \"summary\": {\n    \"incident_date\": \"January 15, 2025\",\n    \"incident_duration\": \"4 hours 37 minutes\",\n    \"affected_users\": \"2.3 million\",\n    \"revenue_impact\": \"$1.2 million\",\n    \"sla_credits\": \"$340,000\"\n  },\n  \"sections\": [\n    {\n      \"title\": \"Executive Summary\",\n      \"content\": \"On January 15, 2025, at 14:23 UTC, our primary production environment experienced a complete service outage lasting 4 hours and 37 minutes, affecting approximately 2.3 million active users across North America and Europe. The root cause was identified as a cascading failure triggered by a database connection pool exhaustion, compounded by inadequate circuit breaker configuration and insufficient monitoring alerts. Total estimated revenue impact is $1.2 million, with an additional $340,000 in SLA credits owed to enterprise customers. Key team members involved: Sarah Martinez, James Kim, Aisha Patel, Rebecca Torres, David Liu, and Marcus Chen.\",\n      \"importance\": \"critical\"\n    },\n    {\n      \"title\": \"Timeline of Events\",\n      \"content\": \"14:23 UTC - Initial alerts triggered for elevated API response times in the us-east-1 region. Average response time increased from baseline 120ms to 3,400ms. On-call engineer Sarah Martinez received PagerDuty notification. 14:26 UTC - Database connection pool utilization reached 98% (490 of 500 connections active). 14:31 UTC - First customer complaints received via support channels. 14:35 UTC - Complete service outage declared. 14:38 UTC - Emergency war room established on Zoom with participants: Marcus Chen, Sarah Martinez, James Kim, Aisha Patel, Rebecca Torres, and David Liu. Initial hypothesis: DDoS attack, later ruled out. Root cause identified: A batch job processing user analytics data, deployed at 13:45 UTC, was opening database connections without proper connection pooling.\",\n      \"importance\": \"high\"\n    },\n    {\n      \"title\": \"Root Cause Analysis\",\n      \"content\": \"The incident was caused by a combination of factors: CODE DEFECT - The analytics batch job contained a critical bug where database connections were created in a loop without using the connection pool manager. INSUFFICIENT TESTING - The batch job was tested in staging environment with only 10,000 sample records, which did not expose the connection leak. MONITORING GAPS - No alerts configured for database connection pool utilization. CIRCUIT BREAKER MISCONFIGURATION - Application-level circuit breakers were configured with a 60-second timeout and 50-failure threshold. DEPLOYMENT PROCESS - The batch job was deployed during peak business hours without following the standard deployment window policy.\",\n      \"importance\": \"critical\"\n    },\n    {\n      \"title\": \"Impact Assessment\",\n      \"content\": \"CUSTOMER IMPACT: 2.3 million active users affected, 4 hours 37 minutes of complete service unavailability, 847 support tickets created, 234 enterprise customers affected, requiring SLA credit compensation. FINANCIAL IMPACT: Direct revenue loss: $1,200,000, SLA credits owed: $340,000, Support overtime costs: $23,000, Engineering overtime: $18,000, Total financial impact: $1,581,000. OPERATIONAL IMPACT: 47 engineers pulled from planned work, Q1 roadmap delayed by 1 week, 3 customer implementations postponed.\",\n      \"importance\": \"high\"\n    },\n    {\n      \"title\": \"Corrective Actions\",\n      \"content\": \"IMMEDIATE: Rolled back analytics batch job to version 2.3.8, Implemented emergency monitoring for database connection pool utilization, Reduced circuit breaker timeout, Increased database connection pool size. SHORT-TERM: Comprehensive code review of all batch jobs, Implement connection pool monitoring dashboard, Update deployment policy, Conduct training session on connection pooling best practices. MEDIUM-TERM: Implement distributed tracing, Deploy chaos engineering tests, Upgrade database infrastructure, Implement automated rollback triggers. LONG-TERM: Migrate to microservices architecture, Implement comprehensive observability platform, Establish formal incident response training program.\",\n      \"importance\": \"high\"\n    },\n    {\n      \"title\": \"Lessons Learned\",\n      \"content\": \"MONITORING IS CRITICAL, TESTING MUST REFLECT PRODUCTION, DEPLOYMENT TIMING MATTERS, CODE REVIEW QUALITY, CIRCUIT BREAKERS NEED TUNING, INCIDENT RESPONSE WORKED WELL\",\n      \"importance\": \"medium\"\n    },\n    {\n      \"title\": \"Recommendations\",\n      \"content\": \"Invest in observability infrastructure, Hire dedicated SRE team, Implement mandatory chaos engineering, Upgrade staging environment, Establish incident response training\",\n      \"importance\": \"medium\"\n    }\n  ],\n  \"constraints\": [\n    \"Complete all corrective actions within specified deadlines\",\n    \"Implement comprehensive monitoring and alerting for database connection pool utilization\",\n    \"Enforce standard deployment window policy\"\n  ],\n  \"state\": {\n    \"incident_status\": \"closed\",\n    \"post_incident_monitoring\": \"in progress\"\n  },\n  \"encoding_strategy\": \"chunked\",\n  \"total_sections\": 7,\n  \"trace_id\": \"512fe650-fe7f-4596-af38-7f11d6cb9c55\",\n  \"timestamp\": \"2026-02-19T09:26:45.598989\",\n  \"parent_id\": null\n}"
  }
}